LICENSE.txt
README.md
setup.py
high5py/__init__.py
high5py/_version.py
high5py/high5py.py
high5py/testhigh5py.py
high5py.egg-info/PKG-INFO
high5py.egg-info/SOURCES.txt
high5py.egg-info/dependency_links.txt
high5py.egg-info/requires.txt
high5py.egg-info/top_level.txt